[
  {
    "Ilce Id": "",
    "Ilce Adi": "",
    "Belde Adi": "",
    "Kayitli Secmen Sayisi": "",
    "Oy Kullanan Secmen Sayisi": "",
    "Gecerli Oy Toplami": "",
    " MILLET ": "",
    " HAK-PAR ": "",
    " TKP ": "",
    " TKH ": "",
    " SOL PARTI ": "",
    " GENCPARTI ": "",
    " MEMLEKET ": "",
    " BBP ": "",
    " AK PARTI ": "",
    " YENIDEN REFAH ": "",
    " MHP ": "",
    " YESIL SOL PARTI ": "",
    " TIP ": "",
    " ANAP ": "",
    " YP ": "",
    " HKP ": "",
    " VATAN PARTISI ": "",
    " GBP ": "",
    " CHP ": "",
    " IYI PARTI ": "",
    " AP ": "",
    " ZAFER PARTISI ": ""
  },
  {
    "Ilce Id": "55",
    "Ilce Adi": " AYANCIK ",
    "Belde Adi": "",
    "Kayitli Secmen Sayisi": " 19.656 ",
    "Oy Kullanan Secmen Sayisi": " 16.778 ",
    "Gecerli Oy Toplami": " 16.115 ",
    " MILLET ": " 22 ",
    " HAK-PAR ": " 49 ",
    " TKP ": " 28 ",
    " TKH ": " 12 ",
    " SOL PARTI ": " 20 ",
    " GENCPARTI ": " 40 ",
    " MEMLEKET ": " 133 ",
    " BBP ": " 306 ",
    " AK PARTI ": " 6.804 ",
    " YENIDEN REFAH ": " 259 ",
    " MHP ": " 2.253 ",
    " YESIL SOL PARTI ": " 55 ",
    " TIP ": " 172 ",
    " ANAP ": " 56 ",
    " YP ": " 8 ",
    " HKP ": " 31 ",
    " VATAN PARTISI ": " 29 ",
    " GBP ": " 23 ",
    " CHP ": " 4.297 ",
    " IYI PARTI ": " 1.188 ",
    " AP ": " 119 ",
    " ZAFER PARTISI ": " 211 "
  },
  {
    "Ilce Id": "Oy Orani",
    "Ilce Adi": "",
    "Belde Adi": " %0.13 ",
    "Kayitli Secmen Sayisi": " %0.3 ",
    "Oy Kullanan Secmen Sayisi": " %0.17 ",
    "Gecerli Oy Toplami": " %0.07 ",
    " MILLET ": " %0.12 ",
    " HAK-PAR ": " %0.24 ",
    " TKP ": " %0.82 ",
    " TKH ": " %1.89 ",
    " SOL PARTI ": " %42.22 ",
    " GENCPARTI ": " %1.6 ",
    " MEMLEKET ": " %13.98 ",
    " BBP ": " %0.34 ",
    " AK PARTI ": " %1.06 ",
    " YENIDEN REFAH ": " %0.34 ",
    " MHP ": " %0.04 ",
    " YESIL SOL PARTI ": " %0.19 ",
    " TIP ": " %0.17 ",
    " ANAP ": " %0.14 ",
    " YP ": " %26.66 ",
    " HKP ": " %7.37 ",
    " VATAN PARTISI ": " %0.73 ",
    " GBP ": " %1.3 ",
    " CHP ": "",
    " IYI PARTI ": "",
    " AP ": "",
    " ZAFER PARTISI ": ""
  },
  {
    "Ilce Id": "",
    "Ilce Adi": "",
    "Belde Adi": "",
    "Kayitli Secmen Sayisi": "",
    "Oy Kullanan Secmen Sayisi": "",
    "Gecerli Oy Toplami": "",
    " MILLET ": "",
    " HAK-PAR ": "",
    " TKP ": "",
    " TKH ": "",
    " SOL PARTI ": "",
    " GENCPARTI ": "",
    " MEMLEKET ": "",
    " BBP ": "",
    " AK PARTI ": "",
    " YENIDEN REFAH ": "",
    " MHP ": "",
    " YESIL SOL PARTI ": "",
    " TIP ": "",
    " ANAP ": "",
    " YP ": "",
    " HKP ": "",
    " VATAN PARTISI ": "",
    " GBP ": "",
    " CHP ": "",
    " IYI PARTI ": "",
    " AP ": "",
    " ZAFER PARTISI ": ""
  },
  {
    "Ilce Id": "103",
    "Ilce Adi": " BOYABAT ",
    "Belde Adi": "",
    "Kayitli Secmen Sayisi": " 33.933 ",
    "Oy Kullanan Secmen Sayisi": " 29.984 ",
    "Gecerli Oy Toplami": " 28.811 ",
    " MILLET ": " 47 ",
    " HAK-PAR ": " 100 ",
    " TKP ": " 37 ",
    " TKH ": " 24 ",
    " SOL PARTI ": " 16 ",
    " GENCPARTI ": " 38 ",
    " MEMLEKET ": " 174 ",
    " BBP ": " 956 ",
    " AK PARTI ": " 14.334 ",
    " YENIDEN REFAH ": " 1.170 ",
    " MHP ": " 3.367 ",
    " YESIL SOL PARTI ": " 71 ",
    " TIP ": " 67 ",
    " ANAP ": " 60 ",
    " YP ": " 132 ",
    " HKP ": " 43 ",
    " VATAN PARTISI ": " 43 ",
    " GBP ": " 17 ",
    " CHP ": " 4.993 ",
    " IYI PARTI ": " 2.501 ",
    " AP ": " 156 ",
    " ZAFER PARTISI ": " 465 "
  },
  {
    "Ilce Id": "Oy Orani",
    "Ilce Adi": "",
    "Belde Adi": " %0.16 ",
    "Kayitli Secmen Sayisi": " %0.34 ",
    "Oy Kullanan Secmen Sayisi": " %0.12 ",
    "Gecerli Oy Toplami": " %0.08 ",
    " MILLET ": " %0.05 ",
    " HAK-PAR ": " %0.13 ",
    " TKP ": " %0.6 ",
    " TKH ": " %3.31 ",
    " SOL PARTI ": " %49.75 ",
    " GENCPARTI ": " %4.06 ",
    " MEMLEKET ": " %11.68 ",
    " BBP ": " %0.24 ",
    " AK PARTI ": " %0.23 ",
    " YENIDEN REFAH ": " %0.2 ",
    " MHP ": " %0.45 ",
    " YESIL SOL PARTI ": " %0.14 ",
    " TIP ": " %0.14 ",
    " ANAP ": " %0.05 ",
    " YP ": " %17.33 ",
    " HKP ": " %8.68 ",
    " VATAN PARTISI ": " %0.54 ",
    " GBP ": " %1.61 ",
    " CHP ": "",
    " IYI PARTI ": "",
    " AP ": "",
    " ZAFER PARTISI ": ""
  },
  {
    "Ilce Id": "",
    "Ilce Adi": "",
    "Belde Adi": "",
    "Kayitli Secmen Sayisi": "",
    "Oy Kullanan Secmen Sayisi": "",
    "Gecerli Oy Toplami": "",
    " MILLET ": "",
    " HAK-PAR ": "",
    " TKP ": "",
    " TKH ": "",
    " SOL PARTI ": "",
    " GENCPARTI ": "",
    " MEMLEKET ": "",
    " BBP ": "",
    " AK PARTI ": "",
    " YENIDEN REFAH ": "",
    " MHP ": "",
    " YESIL SOL PARTI ": "",
    " TIP ": "",
    " ANAP ": "",
    " YP ": "",
    " HKP ": "",
    " VATAN PARTISI ": "",
    " GBP ": "",
    " CHP ": "",
    " IYI PARTI ": "",
    " AP ": "",
    " ZAFER PARTISI ": ""
  },
  {
    "Ilce Id": "803",
    "Ilce Adi": " DIKMEN ",
    "Belde Adi": "",
    "Kayitli Secmen Sayisi": " 4.167 ",
    "Oy Kullanan Secmen Sayisi": " 3.505 ",
    "Gecerli Oy Toplami": " 3.305 ",
    " MILLET ": " 6 ",
    " HAK-PAR ": " 31 ",
    " TKP ": " 10 ",
    " TKH ": " 3 ",
    " SOL PARTI ": " 2 ",
    " GENCPARTI ": " 7 ",
    " MEMLEKET ": " 23 ",
    " BBP ": " 81 ",
    " AK PARTI ": " 1.964 ",
    " YENIDEN REFAH ": " 88 ",
    " MHP ": " 285 ",
    " YESIL SOL PARTI ": " 1 ",
    " TIP ": " 13 ",
    " ANAP ": " 21 ",
    " YP ": " 2 ",
    " HKP ": " 20 ",
    " VATAN PARTISI ": " 20 ",
    " GBP ": " 4 ",
    " CHP ": " 425 ",
    " IYI PARTI ": " 222 ",
    " AP ": " 32 ",
    " ZAFER PARTISI ": " 45 "
  },
  {
    "Ilce Id": "Oy Orani",
    "Ilce Adi": "",
    "Belde Adi": " %0.18 ",
    "Kayitli Secmen Sayisi": " %0.93 ",
    "Oy Kullanan Secmen Sayisi": " %0.3 ",
    "Gecerli Oy Toplami": " %0.09 ",
    " MILLET ": " %0.06 ",
    " HAK-PAR ": " %0.21 ",
    " TKP ": " %0.69 ",
    " TKH ": " %2.45 ",
    " SOL PARTI ": " %59.42 ",
    " GENCPARTI ": " %2.66 ",
    " MEMLEKET ": " %8.62 ",
    " BBP ": " %0.03 ",
    " AK PARTI ": " %0.39 ",
    " YENIDEN REFAH ": " %0.63 ",
    " MHP ": " %0.06 ",
    " YESIL SOL PARTI ": " %0.6 ",
    " TIP ": " %0.6 ",
    " ANAP ": " %0.12 ",
    " YP ": " %12.85 ",
    " HKP ": " %6.71 ",
    " VATAN PARTISI ": " %0.96 ",
    " GBP ": " %1.36 ",
    " CHP ": "",
    " IYI PARTI ": "",
    " AP ": "",
    " ZAFER PARTISI ": ""
  },
  {
    "Ilce Id": "",
    "Ilce Adi": "",
    "Belde Adi": "",
    "Kayitli Secmen Sayisi": "",
    "Oy Kullanan Secmen Sayisi": "",
    "Gecerli Oy Toplami": "",
    " MILLET ": "",
    " HAK-PAR ": "",
    " TKP ": "",
    " TKH ": "",
    " SOL PARTI ": "",
    " GENCPARTI ": "",
    " MEMLEKET ": "",
    " BBP ": "",
    " AK PARTI ": "",
    " YENIDEN REFAH ": "",
    " MHP ": "",
    " YESIL SOL PARTI ": "",
    " TIP ": "",
    " ANAP ": "",
    " YP ": "",
    " HKP ": "",
    " VATAN PARTISI ": "",
    " GBP ": "",
    " CHP ": "",
    " IYI PARTI ": "",
    " AP ": "",
    " ZAFER PARTISI ": ""
  },
  {
    "Ilce Id": "188",
    "Ilce Adi": " DURAGAN ",
    "Belde Adi": "",
    "Kayitli Secmen Sayisi": " 12.976 ",
    "Oy Kullanan Secmen Sayisi": " 11.361 ",
    "Gecerli Oy Toplami": " 10.882 ",
    " MILLET ": " 15 ",
    " HAK-PAR ": " 68 ",
    " TKP ": " 17 ",
    " TKH ": " 14 ",
    " SOL PARTI ": " 7 ",
    " GENCPARTI ": " 8 ",
    " MEMLEKET ": " 36 ",
    " BBP ": " 2.285 ",
    " AK PARTI ": " 6.021 ",
    " YENIDEN REFAH ": " 271 ",
    " MHP ": " 552 ",
    " YESIL SOL PARTI ": " 28 ",
    " TIP ": " 14 ",
    " ANAP ": " 34 ",
    " YP ": " 11 ",
    " HKP ": " 12 ",
    " VATAN PARTISI ": " 20 ",
    " GBP ": " 19 ",
    " CHP ": " 914 ",
    " IYI PARTI ": " 391 ",
    " AP ": " 50 ",
    " ZAFER PARTISI ": " 95 "
  },
  {
    "Ilce Id": "Oy Orani",
    "Ilce Adi": "",
    "Belde Adi": " %0.13 ",
    "Kayitli Secmen Sayisi": " %0.62 ",
    "Oy Kullanan Secmen Sayisi": " %0.15 ",
    "Gecerli Oy Toplami": " %0.12 ",
    " MILLET ": " %0.06 ",
    " HAK-PAR ": " %0.07 ",
    " TKP ": " %0.33 ",
    " TKH ": " %20.99 ",
    " SOL PARTI ": " %55.32 ",
    " GENCPARTI ": " %2.49 ",
    " MEMLEKET ": " %5.07 ",
    " BBP ": " %0.25 ",
    " AK PARTI ": " %0.12 ",
    " YENIDEN REFAH ": " %0.31 ",
    " MHP ": " %0.1 ",
    " YESIL SOL PARTI ": " %0.11 ",
    " TIP ": " %0.18 ",
    " ANAP ": " %0.17 ",
    " YP ": " %8.39 ",
    " HKP ": " %3.59 ",
    " VATAN PARTISI ": " %0.45 ",
    " GBP ": " %0.87 ",
    " CHP ": "",
    " IYI PARTI ": "",
    " AP ": "",
    " ZAFER PARTISI ": ""
  },
  {
    "Ilce Id": "",
    "Ilce Adi": "",
    "Belde Adi": "",
    "Kayitli Secmen Sayisi": "",
    "Oy Kullanan Secmen Sayisi": "",
    "Gecerli Oy Toplami": "",
    " MILLET ": "",
    " HAK-PAR ": "",
    " TKP ": "",
    " TKH ": "",
    " SOL PARTI ": "",
    " GENCPARTI ": "",
    " MEMLEKET ": "",
    " BBP ": "",
    " AK PARTI ": "",
    " YENIDEN REFAH ": "",
    " MHP ": "",
    " YESIL SOL PARTI ": "",
    " TIP ": "",
    " ANAP ": "",
    " YP ": "",
    " HKP ": "",
    " VATAN PARTISI ": "",
    " GBP ": "",
    " CHP ": "",
    " IYI PARTI ": "",
    " AP ": "",
    " ZAFER PARTISI ": ""
  },
  {
    "Ilce Id": "212",
    "Ilce Adi": " ERFELEK ",
    "Belde Adi": "",
    "Kayitli Secmen Sayisi": " 10.563 ",
    "Oy Kullanan Secmen Sayisi": " 9.080 ",
    "Gecerli Oy Toplami": " 8.542 ",
    " MILLET ": " 15 ",
    " HAK-PAR ": " 35 ",
    " TKP ": " 14 ",
    " TKH ": " 12 ",
    " SOL PARTI ": " 11 ",
    " GENCPARTI ": " 15 ",
    " MEMLEKET ": " 52 ",
    " BBP ": " 132 ",
    " AK PARTI ": " 4.107 ",
    " YENIDEN REFAH ": " 147 ",
    " MHP ": " 313 ",
    " YESIL SOL PARTI ": " 25 ",
    " TIP ": " 35 ",
    " ANAP ": " 49 ",
    " YP ": " 4 ",
    " HKP ": " 21 ",
    " VATAN PARTISI ": " 16 ",
    " GBP ": " 17 ",
    " CHP ": " 2.575 ",
    " IYI PARTI ": " 734 ",
    " AP ": " 133 ",
    " ZAFER PARTISI ": " 80 "
  },
  {
    "Ilce Id": "Oy Orani",
    "Ilce Adi": "",
    "Belde Adi": " %0.17 ",
    "Kayitli Secmen Sayisi": " %0.4 ",
    "Oy Kullanan Secmen Sayisi": " %0.16 ",
    "Gecerli Oy Toplami": " %0.14 ",
    " MILLET ": " %0.12 ",
    " HAK-PAR ": " %0.17 ",
    " TKP ": " %0.6 ",
    " TKH ": " %1.54 ",
    " SOL PARTI ": " %48.08 ",
    " GENCPARTI ": " %1.72 ",
    " MEMLEKET ": " %3.66 ",
    " BBP ": " %0.29 ",
    " AK PARTI ": " %0.4 ",
    " YENIDEN REFAH ": " %0.57 ",
    " MHP ": " %0.04 ",
    " YESIL SOL PARTI ": " %0.24 ",
    " TIP ": " %0.18 ",
    " ANAP ": " %0.19 ",
    " YP ": " %30.14 ",
    " HKP ": " %8.59 ",
    " VATAN PARTISI ": " %1.55 ",
    " GBP ": " %0.93 ",
    " CHP ": "",
    " IYI PARTI ": "",
    " AP ": "",
    " ZAFER PARTISI ": ""
  },
  {
    "Ilce Id": "",
    "Ilce Adi": "",
    "Belde Adi": "",
    "Kayitli Secmen Sayisi": "",
    "Oy Kullanan Secmen Sayisi": "",
    "Gecerli Oy Toplami": "",
    " MILLET ": "",
    " HAK-PAR ": "",
    " TKP ": "",
    " TKH ": "",
    " SOL PARTI ": "",
    " GENCPARTI ": "",
    " MEMLEKET ": "",
    " BBP ": "",
    " AK PARTI ": "",
    " YENIDEN REFAH ": "",
    " MHP ": "",
    " YESIL SOL PARTI ": "",
    " TIP ": "",
    " ANAP ": "",
    " YP ": "",
    " HKP ": "",
    " VATAN PARTISI ": "",
    " GBP ": "",
    " CHP ": "",
    " IYI PARTI ": "",
    " AP ": "",
    " ZAFER PARTISI ": ""
  },
  {
    "Ilce Id": "246",
    "Ilce Adi": " GERZE ",
    "Belde Adi": "",
    "Kayitli Secmen Sayisi": " 23.102 ",
    "Oy Kullanan Secmen Sayisi": " 20.359 ",
    "Gecerli Oy Toplami": " 19.290 ",
    " MILLET ": " 50 ",
    " HAK-PAR ": " 72 ",
    " TKP ": " 35 ",
    " TKH ": " 10 ",
    " SOL PARTI ": " 14 ",
    " GENCPARTI ": " 41 ",
    " MEMLEKET ": " 200 ",
    " BBP ": " 702 ",
    " AK PARTI ": " 8.373 ",
    " YENIDEN REFAH ": " 409 ",
    " MHP ": " 1.588 ",
    " YESIL SOL PARTI ": " 57 ",
    " TIP ": " 159 ",
    " ANAP ": " 81 ",
    " YP ": " 14 ",
    " HKP ": " 50 ",
    " VATAN PARTISI ": " 26 ",
    " GBP ": " 14 ",
    " CHP ": " 5.364 ",
    " IYI PARTI ": " 1.520 ",
    " AP ": " 171 ",
    " ZAFER PARTISI ": " 340 "
  },
  {
    "Ilce Id": "Oy Orani",
    "Ilce Adi": "",
    "Belde Adi": " %0.25 ",
    "Kayitli Secmen Sayisi": " %0.37 ",
    "Oy Kullanan Secmen Sayisi": " %0.18 ",
    "Gecerli Oy Toplami": " %0.05 ",
    " MILLET ": " %0.07 ",
    " HAK-PAR ": " %0.21 ",
    " TKP ": " %1.03 ",
    " TKH ": " %3.63 ",
    " SOL PARTI ": " %43.4 ",
    " GENCPARTI ": " %2.12 ",
    " MEMLEKET ": " %8.23 ",
    " BBP ": " %0.29 ",
    " AK PARTI ": " %0.82 ",
    " YENIDEN REFAH ": " %0.41 ",
    " MHP ": " %0.07 ",
    " YESIL SOL PARTI ": " %0.25 ",
    " TIP ": " %0.13 ",
    " ANAP ": " %0.07 ",
    " YP ": " %27.8 ",
    " HKP ": " %7.87 ",
    " VATAN PARTISI ": " %0.88 ",
    " GBP ": " %1.76 ",
    " CHP ": "",
    " IYI PARTI ": "",
    " AP ": "",
    " ZAFER PARTISI ": ""
  },
  {
    "Ilce Id": "",
    "Ilce Adi": "",
    "Belde Adi": "",
    "Kayitli Secmen Sayisi": "",
    "Oy Kullanan Secmen Sayisi": "",
    "Gecerli Oy Toplami": "",
    " MILLET ": "",
    " HAK-PAR ": "",
    " TKP ": "",
    " TKH ": "",
    " SOL PARTI ": "",
    " GENCPARTI ": "",
    " MEMLEKET ": "",
    " BBP ": "",
    " AK PARTI ": "",
    " YENIDEN REFAH ": "",
    " MHP ": "",
    " YESIL SOL PARTI ": "",
    " TIP ": "",
    " ANAP ": "",
    " YP ": "",
    " HKP ": "",
    " VATAN PARTISI ": "",
    " GBP ": "",
    " CHP ": "",
    " IYI PARTI ": "",
    " AP ": "",
    " ZAFER PARTISI ": ""
  },
  {
    "Ilce Id": "874",
    "Ilce Adi": " SARAYDUZU ",
    "Belde Adi": "",
    "Kayitli Secmen Sayisi": " 4.955 ",
    "Oy Kullanan Secmen Sayisi": " 4.298 ",
    "Gecerli Oy Toplami": " 4.076 ",
    " MILLET ": " 4 ",
    " HAK-PAR ": " 11 ",
    " TKP ": " 3 ",
    " TKH ": " 6 ",
    " SOL PARTI ": " 1 ",
    " GENCPARTI ": " 9 ",
    " MEMLEKET ": " 11 ",
    " BBP ": " 68 ",
    " AK PARTI ": " 2.164 ",
    " YENIDEN REFAH ": " 123 ",
    " MHP ": " 788 ",
    " YESIL SOL PARTI ": " 4 ",
    " TIP ": " 12 ",
    " ANAP ": " 17 ",
    " YP ": " 4 ",
    " HKP ": " 8 ",
    " VATAN PARTISI ": " 5 ",
    " GBP ": " 3 ",
    " CHP ": " 519 ",
    " IYI PARTI ": " 243 ",
    " AP ": " 41 ",
    " ZAFER PARTISI ": " 32 "
  },
  {
    "Ilce Id": "Oy Orani",
    "Ilce Adi": "",
    "Belde Adi": " %0.09 ",
    "Kayitli Secmen Sayisi": " %0.26 ",
    "Oy Kullanan Secmen Sayisi": " %0.07 ",
    "Gecerli Oy Toplami": " %0.14 ",
    " MILLET ": " %0.02 ",
    " HAK-PAR ": " %0.22 ",
    " TKP ": " %0.26 ",
    " TKH ": " %1.66 ",
    " SOL PARTI ": " %53.09 ",
    " GENCPARTI ": " %3.01 ",
    " MEMLEKET ": " %19.33 ",
    " BBP ": " %0.09 ",
    " AK PARTI ": " %0.29 ",
    " YENIDEN REFAH ": " %0.41 ",
    " MHP ": " %0.09 ",
    " YESIL SOL PARTI ": " %0.19 ",
    " TIP ": " %0.12 ",
    " ANAP ": " %0.07 ",
    " YP ": " %12.73 ",
    " HKP ": " %5.96 ",
    " VATAN PARTISI ": " %1 ",
    " GBP ": " %0.78 ",
    " CHP ": "",
    " IYI PARTI ": "",
    " AP ": "",
    " ZAFER PARTISI ": ""
  },
  {
    "Ilce Id": "",
    "Ilce Adi": "",
    "Belde Adi": "",
    "Kayitli Secmen Sayisi": "",
    "Oy Kullanan Secmen Sayisi": "",
    "Gecerli Oy Toplami": "",
    " MILLET ": "",
    " HAK-PAR ": "",
    " TKP ": "",
    " TKH ": "",
    " SOL PARTI ": "",
    " GENCPARTI ": "",
    " MEMLEKET ": "",
    " BBP ": "",
    " AK PARTI ": "",
    " YENIDEN REFAH ": "",
    " MHP ": "",
    " YESIL SOL PARTI ": "",
    " TIP ": "",
    " ANAP ": "",
    " YP ": "",
    " HKP ": "",
    " VATAN PARTISI ": "",
    " GBP ": "",
    " CHP ": "",
    " IYI PARTI ": "",
    " AP ": "",
    " ZAFER PARTISI ": ""
  },
  {
    "Ilce Id": "520",
    "Ilce Adi": " SINOP MERKEZ ",
    "Belde Adi": "",
    "Kayitli Secmen Sayisi": " 49.981 ",
    "Oy Kullanan Secmen Sayisi": " 45.112 ",
    "Gecerli Oy Toplami": " 43.799 ",
    " MILLET ": " 55 ",
    " HAK-PAR ": " 48 ",
    " TKP ": " 59 ",
    " TKH ": " 22 ",
    " SOL PARTI ": " 30 ",
    " GENCPARTI ": " 69 ",
    " MEMLEKET ": " 666 ",
    " BBP ": " 1.801 ",
    " AK PARTI ": " 13.265 ",
    " YENIDEN REFAH ": " 578 ",
    " MHP ": " 1.703 ",
    " YESIL SOL PARTI ": " 225 ",
    " TIP ": " 600 ",
    " ANAP ": " 87 ",
    " YP ": " 14 ",
    " HKP ": " 33 ",
    " VATAN PARTISI ": " 49 ",
    " GBP ": " 51 ",
    " CHP ": " 16.992 ",
    " IYI PARTI ": " 6.478 ",
    " AP ": " 199 ",
    " ZAFER PARTISI ": " 775 "
  },
  {
    "Ilce Id": "Oy Orani",
    "Ilce Adi": "",
    "Belde Adi": " %0.12 ",
    "Kayitli Secmen Sayisi": " %0.1 ",
    "Oy Kullanan Secmen Sayisi": " %0.13 ",
    "Gecerli Oy Toplami": " %0.05 ",
    " MILLET ": " %0.06 ",
    " HAK-PAR ": " %0.15 ",
    " TKP ": " %1.52 ",
    " TKH ": " %4.11 ",
    " SOL PARTI ": " %30.28 ",
    " GENCPARTI ": " %1.31 ",
    " MEMLEKET ": " %3.88 ",
    " BBP ": " %0.51 ",
    " AK PARTI ": " %1.36 ",
    " YENIDEN REFAH ": " %0.19 ",
    " MHP ": " %0.03 ",
    " YESIL SOL PARTI ": " %0.07 ",
    " TIP ": " %0.11 ",
    " ANAP ": " %0.11 ",
    " YP ": " %38.79 ",
    " HKP ": " %14.79 ",
    " VATAN PARTISI ": " %0.45 ",
    " GBP ": " %1.76 ",
    " CHP ": "",
    " IYI PARTI ": "",
    " AP ": "",
    " ZAFER PARTISI ": ""
  },
  {
    "Ilce Id": "",
    "Ilce Adi": "",
    "Belde Adi": "",
    "Kayitli Secmen Sayisi": "",
    "Oy Kullanan Secmen Sayisi": "",
    "Gecerli Oy Toplami": "",
    " MILLET ": "",
    " HAK-PAR ": "",
    " TKP ": "",
    " TKH ": "",
    " SOL PARTI ": "",
    " GENCPARTI ": "",
    " MEMLEKET ": "",
    " BBP ": "",
    " AK PARTI ": "",
    " YENIDEN REFAH ": "",
    " MHP ": "",
    " YESIL SOL PARTI ": "",
    " TIP ": "",
    " ANAP ": "",
    " YP ": "",
    " HKP ": "",
    " VATAN PARTISI ": "",
    " GBP ": "",
    " CHP ": "",
    " IYI PARTI ": "",
    " AP ": "",
    " ZAFER PARTISI ": ""
  },
  {
    "Ilce Id": "586",
    "Ilce Adi": " TURKELI ",
    "Belde Adi": "",
    "Kayitli Secmen Sayisi": " 12.510 ",
    "Oy Kullanan Secmen Sayisi": " 10.370 ",
    "Gecerli Oy Toplami": " 9.981 ",
    " MILLET ": " 16 ",
    " HAK-PAR ": " 36 ",
    " TKP ": " 18 ",
    " TKH ": " 3 ",
    " SOL PARTI ": " 8 ",
    " GENCPARTI ": " 15 ",
    " MEMLEKET ": " 72 ",
    " BBP ": " 238 ",
    " AK PARTI ": " 4.781 ",
    " YENIDEN REFAH ": " 259 ",
    " MHP ": " 2.300 ",
    " YESIL SOL PARTI ": " 31 ",
    " TIP ": " 42 ",
    " ANAP ": " 33 ",
    " YP ": " 4 ",
    " HKP ": " 19 ",
    " VATAN PARTISI ": " 17 ",
    " GBP ": " 8 ",
    " CHP ": " 1.237 ",
    " IYI PARTI ": " 645 ",
    " AP ": " 61 ",
    " ZAFER PARTISI ": " 138 "
  },
  {
    "Ilce Id": "Oy Orani",
    "Ilce Adi": "",
    "Belde Adi": " %0.16 ",
    "Kayitli Secmen Sayisi": " %0.36 ",
    "Oy Kullanan Secmen Sayisi": " %0.18 ",
    "Gecerli Oy Toplami": " %0.03 ",
    " MILLET ": " %0.08 ",
    " HAK-PAR ": " %0.15 ",
    " TKP ": " %0.72 ",
    " TKH ": " %2.38 ",
    " SOL PARTI ": " %47.9 ",
    " GENCPARTI ": " %2.59 ",
    " MEMLEKET ": " %23.04 ",
    " BBP ": " %0.31 ",
    " AK PARTI ": " %0.42 ",
    " YENIDEN REFAH ": " %0.33 ",
    " MHP ": " %0.04 ",
    " YESIL SOL PARTI ": " %0.19 ",
    " TIP ": " %0.17 ",
    " ANAP ": " %0.08 ",
    " YP ": " %12.39 ",
    " HKP ": " %6.46 ",
    " VATAN PARTISI ": " %0.61 ",
    " GBP ": " %1.38 ",
    " CHP ": "",
    " IYI PARTI ": "",
    " AP ": "",
    " ZAFER PARTISI ": ""
  }
]